ton/__init__.py
the_open_network-0.1.dist-info/METADATA
the_open_network-0.1.dist-info/WHEEL
the_open_network-0.1.dist-info/top_level.txt
the_open_network-0.1.dist-info/RECORD
