Metadata-Version: 2.1
Name: the-open-network
Version: 0.1
Summary: Just wait for a new module based on tonapi.io :D
Author-email: ZAID <y8838@hotmail.com>
License: MIT License
Keywords: ton,tonapi,pyton,blockchain,crypto
